codecipher/__init__.py
codecipher/py.typed
codecipher/a1z52n62/__init__.py
codecipher/a1z52n62/decode.py
codecipher/a1z52n62/encode.py
codecipher/atbs/__init__.py
codecipher/atbs/decode.py
codecipher/atbs/encode.py
codecipher/atbs/lookup_table.py
codecipher/b64/__init__.py
codecipher/b64/decode.py
codecipher/b64/encode.py
codecipher/caesar/__init__.py
codecipher/caesar/decode.py
codecipher/caesar/encode.py
codecipher/vernam/__init__.py
codecipher/vernam/decode.py
codecipher/vernam/encode.py
codecipher/vigenere/__init__.py
codecipher/vigenere/decode.py
codecipher/vigenere/encode.py
codecipher/vigenere/key_generator.py
codecipher/vigenere/lookup_table.py
codecipher-1.5.0.dist-info/licenses/LICENSE
codecipher-1.5.0.dist-info/METADATA
codecipher-1.5.0.dist-info/WHEEL
codecipher-1.5.0.dist-info/top_level.txt
codecipher-1.5.0.dist-info/RECORD
